pack2skill/__init__.py
pack2skill/__main__.py
pack2skill/cli/__init__.py
pack2skill/cli/main.py
pack2skill/core/__init__.py
pack2skill/core/analyzer/__init__.py
pack2skill/core/analyzer/caption_generator.py
pack2skill/core/analyzer/frame_analyzer.py
pack2skill/core/analyzer/frame_extractor.py
pack2skill/core/generator/__init__.py
pack2skill/core/generator/skill_formatter.py
pack2skill/core/generator/skill_generator.py
pack2skill/core/recorder/__init__.py
pack2skill/core/recorder/event_recorder.py
pack2skill/core/recorder/screen_recorder.py
pack2skill/core/recorder/workflow_recorder.py
pack2skill/core/utils/__init__.py
pack2skill/quality/__init__.py
pack2skill/quality/confidence.py
pack2skill/quality/description.py
pack2skill/quality/robustness.py
pack2skill/team/__init__.py
pack2skill/team/versioning.py
pack2skill-0.1.0.dist-info/licenses/LICENSE
pack2skill-0.1.0.dist-info/METADATA
pack2skill-0.1.0.dist-info/WHEEL
pack2skill-0.1.0.dist-info/entry_points.txt
pack2skill-0.1.0.dist-info/top_level.txt
pack2skill-0.1.0.dist-info/RECORD
