Metadata-Version: 2.4
Name: pack2skill
Version: 0.1.0
Summary: Transform workflows into Claude Skills automatically
Home-page: https://github.com/jmanhype/pack2skill
Author: Pack2Skill Team
Author-email: Pack2Skill Team <contact@pack2skill.dev>
License: MIT
Project-URL: Homepage, https://github.com/jmanhype/pack2skill
Project-URL: Documentation, https://github.com/jmanhype/pack2skill#readme
Project-URL: Repository, https://github.com/jmanhype/pack2skill
Project-URL: Issues, https://github.com/jmanhype/pack2skill/issues
Project-URL: Changelog, https://github.com/jmanhype/pack2skill/releases
Keywords: claude,claude-skills,workflow-automation,skill-generation,ai
Classifier: Development Status :: 3 - Alpha
Classifier: Intended Audience :: Developers
Classifier: License :: OSI Approved :: MIT License
Classifier: Programming Language :: Python :: 3
Classifier: Programming Language :: Python :: 3.9
Classifier: Programming Language :: Python :: 3.10
Classifier: Programming Language :: Python :: 3.11
Classifier: Programming Language :: Python :: 3.12
Classifier: Topic :: Software Development :: Code Generators
Classifier: Topic :: Multimedia :: Video :: Capture
Requires-Python: >=3.9
License-File: LICENSE
Requires-Dist: transformers>=4.35.0
Requires-Dist: torch>=2.0.0
Requires-Dist: pillow>=10.0.0
Requires-Dist: opencv-python>=4.8.0
Requires-Dist: pytesseract>=0.3.10
Requires-Dist: pynput>=1.7.6
Requires-Dist: pyyaml>=6.0
Requires-Dist: openai>=1.0.0
Requires-Dist: anthropic>=0.7.0
Requires-Dist: ffmpeg-python>=0.2.0
Requires-Dist: click>=8.1.0
Requires-Dist: tqdm>=4.65.0
Requires-Dist: python-dateutil>=2.8.2
Requires-Dist: requests>=2.31.0
Provides-Extra: dev
Requires-Dist: pytest>=7.4.0; extra == "dev"
Requires-Dist: pytest-cov>=4.1.0; extra == "dev"
Requires-Dist: pytest-asyncio>=0.21.0; extra == "dev"
Requires-Dist: black>=23.0.0; extra == "dev"
Requires-Dist: flake8>=6.0.0; extra == "dev"
Requires-Dist: mypy>=1.5.0; extra == "dev"
Requires-Dist: pre-commit>=3.3.0; extra == "dev"
Dynamic: author
Dynamic: home-page
Dynamic: license-file
Dynamic: requires-python
